adafruit_raspberry_pi5_neopixel_write.cpython-311-arm-linux-gnueabihf.so
Adafruit_Blinka_Raspberry_Pi5_Neopixel-1.0.0rc1.dist-info/top_level.txt
Adafruit_Blinka_Raspberry_Pi5_Neopixel-1.0.0rc1.dist-info/RECORD
Adafruit_Blinka_Raspberry_Pi5_Neopixel-1.0.0rc1.dist-info/LICENSE
Adafruit_Blinka_Raspberry_Pi5_Neopixel-1.0.0rc1.dist-info/METADATA
Adafruit_Blinka_Raspberry_Pi5_Neopixel-1.0.0rc1.dist-info/WHEEL
